imap_mailbox/__init__.py
imap_mailbox-0.3.0.dist-info/WHEEL
imap_mailbox-0.3.0.dist-info/METADATA
imap_mailbox-0.3.0.dist-info/RECORD
