Metadata-Version: 2.4
Name: imap-mailbox
Version: 0.3.0
Summary: mailbox over IMAP
Author: Pedro Rodrigues
Author-email: Pedro Rodrigues <medecau@gmail.com>
License-Expression: MIT
Requires-Python: >=3.11
Project-URL: Documentation, https://medecau.github.io/imap_mailbox/
Project-URL: Homepage, https://medecau.github.io/imap_mailbox/
Project-URL: Repository, https://github.com/medecau/imap_mailbox
